retain/__init__.py
retain-1.3.0.dist-info/LICENSE.md
retain-1.3.0.dist-info/METADATA
retain-1.3.0.dist-info/WHEEL
retain-1.3.0.dist-info/entry_points.txt
retain-1.3.0.dist-info/top_level.txt
retain-1.3.0.dist-info/RECORD
