Metadata-Version: 2.1
Name: retain
Version: 1.3.0
Home-page: https://github.com/bmc/retain
Author: Brian Clapper
Author-email: bmc@clapper.org
License: Apache Software License
Classifier: Intended Audience :: Developers
Classifier: Intended Audience :: System Administrators
Classifier: License :: OSI Approved :: Apache Software License
Classifier: Programming Language :: Python
Classifier: Topic :: Utilities
License-File: LICENSE.md
Requires-Dist: click (>=8.0.0)
